{"key": "2e4d4682e6421be9", "label": "Software Engineer Austin Texas", "source": "seed", "stored_at": 1775060150.736465, "job_count": 2, "jobs": [{"job": {"id": "e9c9f438dafa", "title": "Sr Software Engineer, Search", "company": "Databricks", "location": "Bengaluru, India", "remote": false, "url": "https://databricks.com/company/careers/open-positions/job?gh_jid=7958967002", "description": "", "salary_text": "", "salary_min": null, "salary_max": null, "date_posted": "2026-02-19", "source": "greenhouse", "source_type": "public_api", "raw": {}}, "score": {"fit_score": 0.8, "reasoning": "Good match in skills", "matching_skills": ["software development", "engineering"], "missing_skills": ["distributed systems", "cloud computing", "agile development"], "red_flags": [], "salary_range": null}}, {"job": {"id": "924abbd022fd", "title": "Sr Software Engineer, Search Relevance (Applied AI)", "company": "Databricks", "location": "Bengaluru, India", "remote": false, "url": "https://databricks.com/company/careers/open-positions/job?gh_jid=7958676002", "description": "", "salary_text": "", "salary_min": null, "salary_max": null, "date_posted": "2026-02-19", "source": "greenhouse", "source_type": "public_api", "raw": {}}, "score": {"fit_score": 0.8, "reasoning": "Good match in skills", "matching_skills": ["software development", "engineering"], "missing_skills": ["distributed systems", "cloud computing", "agile development"], "red_flags": [], "salary_range": null}}], "hot_skills": [{"skill": "software development", "count": 2}, {"skill": "engineering", "count": 2}, {"skill": "distributed systems", "count": 2}, {"skill": "cloud computing", "count": 2}, {"skill": "agile development", "count": 2}]}